<?xml version="1.0" encoding="utf-8" ?>
<dwsync>
<file name="Dani.jpg" server="www.rso.cornell.edu" local="129299478987750434" remote="129482043600000000" />
<file name="Dani2.jpg" server="www.rso.cornell.edu" local="129299478987760434" remote="129299623800000000" />
<file name="danielle.JPG" server="www.rso.cornell.edu" local="129299478987770435" remote="129299623800000000" />
<file name="fan.JPG" server="www.rso.cornell.edu" local="129299478987780435" remote="129482043600000000" />
<file name="Grace.jpg" server="www.rso.cornell.edu" local="129299478987790436" remote="129299623800000000" />
<file name="haiyan.JPG" server="www.rso.cornell.edu" local="129299478987800436" remote="129482043600000000" />
<file name="haolin.JPG" server="www.rso.cornell.edu" local="129299478987820438" remote="129482043600000000" />
<file name="Hongyan.jpg" server="www.rso.cornell.edu" local="129299478987830438" remote="129482043600000000" />
<file name="Janet.jpg" server="www.rso.cornell.edu" local="129299478987840439" remote="129482043600000000" />
<file name="jenny.JPG" server="www.rso.cornell.edu" local="129299478987840439" remote="129482043600000000" />
<file name="Jiali.jpg" server="www.rso.cornell.edu" local="129299478987850439" remote="129482043600000000" />
<file name="Jing.jpg" server="www.rso.cornell.edu" local="129299478987860440" remote="129482043600000000" />
<file name="ling.jpg" server="www.rso.cornell.edu" local="129299478987870440" remote="129482043600000000" />
<file name="Lisa.jpg" server="www.rso.cornell.edu" local="129299478987880441" remote="129482043600000000" />
<file name="lucy.jpg" server="www.rso.cornell.edu" local="129299478987890442" remote="129482043600000000" />
<file name="Luyang.jpg" server="www.rso.cornell.edu" local="129299478987900442" remote="129482043600000000" />
<file name="Lv.JPG" server="www.rso.cornell.edu" local="129299478987910443" remote="129482043600000000" />
<file name="Maria.JPG" server="www.rso.cornell.edu" local="129299478987920443" remote="129299623800000000" />
<file name="Maria_1.JPG" server="www.rso.cornell.edu" local="129299478987930444" remote="129299623800000000" />
<file name="Peijun.jpg" server="www.rso.cornell.edu" local="129299478987940444" remote="129482043600000000" />
<file name="Selina.jpg" server="www.rso.cornell.edu" local="129299478987950445" remote="129482043000000000" />
<file name="Shelley.jpg" server="www.rso.cornell.edu" local="129299478987960446" remote="129299623800000000" />
<file name="Shu.jpg" server="www.rso.cornell.edu" local="129299478987970446" remote="129482043600000000" />
<file name="Tingting.jpg" server="www.rso.cornell.edu" local="129299478987980447" remote="129482049600000000" />
<file name="Wenny.jpg" server="www.rso.cornell.edu" local="129299478987990447" remote="129482043600000000" />
<file name="Willie.JPG" server="www.rso.cornell.edu" local="129299478988000448" remote="129299623800000000" />
<file name="Xiaoqing.jpg" server="www.rso.cornell.edu" local="129299478988010448" remote="129482043600000000" />
<file name="Yao.JPG" server="www.rso.cornell.edu" local="129299478988020449" remote="129482043600000000" />
<file name="Yinan.jpg" server="www.rso.cornell.edu" local="129299478988030450" remote="129482049600000000" />
<file name="Ying.jpg" server="www.rso.cornell.edu" local="129299478988040450" remote="129482043600000000" />
<file name="Maria.jpg" server="www.rso.cornell.edu" local="129299478987920443" remote="129482043000000000" />
<file name="Dani.JPG" server="www.rso.cornell.edu" local="129299478987750434" remote="129299625000000000" />
<file name="Yu-Fang.jpg" server="www.rso.cornell.edu" local="129300848500392917" remote="129300997800000000" />
<file name="Svet.jpg" server="www.rso.cornell.edu" local="129300848274169977" remote="129482043000000000" />
<file name="Yu-fang.jpg" server="www.rso.cornell.edu" local="129300848500392917" remote="129482043000000000" />
<file name="Xiaonan.jpg" server="www.rso.cornell.edu" local="129481862893137919" remote="129482043000000000" />
<file name="Eve.jpg" server="www.rso.cornell.edu" local="129481864558993200" remote="129482043000000000" />
<file name="Yunxia.jpg" server="www.rso.cornell.edu" local="129481866906547473" remote="129482043000000000" />
<file name="Grace.JPG" server="www.rso.cornell.edu" local="129299478987790436" remote="129482043000000000" />
<file name="Siyu.jpg" server="www.rso.cornell.edu" local="129481870810330756" remote="129482043000000000" />
<file name="Shelley.JPG" server="www.rso.cornell.edu" local="129299478987960446" remote="129482043000000000" />
<file name="Yunie.JPG" server="www.rso.cornell.edu" local="129481875153899194" remote="129482043000000000" />
<file name="Lee.jpg" server="www.rso.cornell.edu" local="129481897990675383" remote="129482043000000000" />
<file name="Willie.jpg" server="www.rso.cornell.edu" local="129299478988000448" remote="129482043600000000" />
<file name="Wengyao.jpg" server="www.rso.cornell.edu" local="129481878307989598" remote="129482043600000000" />
<file name="Yiyi.jpg" server="www.rso.cornell.edu" local="129481888057487237" remote="129482043600000000" />
</dwsync>